{
    "type": "Collection",
    "id": "landsat-c2l2-sr-lakes-vanern",
    "stac_version": "1.0.0",
    "description": "Selected low-cloud-cover Landsat Collection-2 Level-2 Surface Reflectance scenes covering V\u00e4nern. Products from multiple missions and instruments are combined in this single collection for the purpose of visualizing RGB images. Note that the full item records are not interchangeable across instruments for purposes other than visualization and that the assets available are not the same for each instrument.",
    "links": [],
    "stac_extensions": [
        "https://stac-extensions.github.io/item-assets/v1.0.0/schema.json"
    ],
    "item_assets": {
        "red": {
            "type": "image/vnd.stac.geotiff; cloud-optimized=true",
            "roles": [
                "data"
            ],
            "title": "Red Band (B4)",
            "eo:bands": [
                {
                    "gsd": 30,
                    "name": "B4",
                    "common_name": "red",
                    "center_wavelength": 0.65
                }
            ],
            "description": "Collection 2 Level-2 Red Band (B4) Surface Reflectance"
        },
        "blue": {
            "type": "image/vnd.stac.geotiff; cloud-optimized=true",
            "roles": [
                "data"
            ],
            "title": "Blue Band (B2)",
            "eo:bands": [
                {
                    "gsd": 30,
                    "name": "B2",
                    "common_name": "blue",
                    "center_wavelength": 0.48
                }
            ],
            "description": "Collection 2 Level-2 Blue Band (B2) Surface Reflectance"
        },
        "green": {
            "type": "image/vnd.stac.geotiff; cloud-optimized=true",
            "roles": [
                "data"
            ],
            "title": "Green Band (B3)",
            "eo:bands": [
                {
                    "gsd": 30,
                    "name": "B3",
                    "common_name": "green",
                    "center_wavelength": 0.56
                }
            ],
            "description": "Collection 2 Level-2 Green Band (B3) Surface Reflectance"
        },
        "thumbnail": {
            "type": "image/jpeg",
            "roles": [
                "thumbnail"
            ],
            "title": "Thumbnail image"
        }
    },
    "dashboard:is_periodic": false,
    "dashboard:time_density": "day",
    "title": "Selected Landsat 7 through 9 Surface Reflectance Scenes for V\u00e4nern",
    "extent": {
        "spatial": {
            "bbox": [
                [
                    10.9716044,
                    57.4228267,
                    15.8602295,
                    59.7931386
                ]
            ]
        },
        "temporal": {
            "interval": [
                [
                    "1984-04-18T09:40:30.064088Z",
                    "2023-06-09T10:12:43.999938Z"
                ]
            ]
        }
    },
    "license": "proprietary",
    "providers": [
        {
            "name": "NASA VEDA",
            "roles": [
                "host"
            ],
            "url": "https://www.earthdata.nasa.gov/dashboard/"
        }
    ],
    "summaries": {
        "datetime": [
            "1984-04-18T09:40:30Z",
            "1984-05-20T09:41:04Z",
            "1985-05-07T09:43:26Z",
            "1985-07-10T09:43:17Z",
            "1985-07-26T09:43:10Z",
            "1985-09-12T09:42:38Z",
            "1985-09-28T09:42:27Z",
            "1986-04-08T09:38:54Z",
            "1986-06-27T09:36:41Z",
            "1986-10-17T09:32:50Z",
            "1986-11-02T09:32:16Z",
            "1987-10-04T09:40:35Z",
            "1988-03-12T09:43:13Z",
            "1988-05-15T09:43:42Z",
            "1989-02-11T09:43:19Z",
            "1989-05-18T09:41:44Z",
            "1989-07-05T09:40:54Z",
            "1989-08-22T09:39:52Z",
            "1990-05-05T09:33:28Z",
            "1991-05-08T09:35:40Z",
            "1991-07-27T09:36:47Z",
            "1992-06-11T09:36:44Z",
            "1993-02-22T09:35:16Z",
            "1993-06-30T09:35:44Z",
            "1993-09-18T09:35:38Z",
            "1994-06-01T09:32:31Z",
            "1994-07-19T09:31:22Z",
            "1994-08-04T09:30:54Z",
            "1995-08-23T09:16:22Z",
            "1997-04-06T09:40:19Z",
            "2000-03-05T10:05:55Z",
            "2000-03-29T09:47:41Z",
            "2000-05-08T10:05:28Z",
            "2000-05-16T09:49:06Z",
            "2000-06-17T09:49:43Z",
            "2000-07-03T09:50:05Z",
            "2000-08-12T10:04:24Z",
            "2001-03-24T10:03:30Z",
            "2001-05-11T10:03:16Z",
            "2002-04-28T10:02:08Z",
            "2002-05-14T10:02:02Z",
            "2002-05-22T09:50:04Z",
            "2002-06-07T09:49:47Z",
            "2002-07-17T10:01:39Z",
            "2002-08-18T10:01:28Z",
            "2002-09-03T10:01:19Z",
            "2003-03-14T10:02:03Z",
            "2003-03-30T10:02:01Z",
            "2003-08-05T10:01:42Z",
            "2003-08-29T09:50:33Z",
            "2004-02-21T09:52:16Z",
            "2004-04-01T10:02:35Z",
            "2004-04-09T09:52:50Z",
            "2004-08-07T10:02:07Z",
            "2004-08-23T10:02:06Z",
            "2004-09-16T09:57:11Z",
            "2004-10-10T10:01:50Z",
            "2005-03-03T10:03:00Z",
            "2005-03-19T10:03:01Z",
            "2005-04-28T10:00:30Z",
            "2006-04-15T10:05:01Z",
            "2006-04-23T10:03:20Z",
            "2006-06-10T10:03:20Z",
            "2006-08-05T10:06:38Z",
            "2006-09-14T10:02:52Z",
            "2006-09-22T10:07:11Z",
            "2007-04-02T10:08:12Z",
            "2007-08-24T10:06:34Z",
            "2008-03-27T10:03:28Z",
            "2008-07-25T09:59:51Z",
            "2009-04-23T10:00:39Z",
            "2009-05-01T10:03:43Z",
            "2009-05-25T10:01:16Z",
            "2009-06-26T10:01:51Z",
            "2010-07-07T10:05:32Z",
            "2010-10-11T10:05:39Z",
            "2010-11-04T10:03:08Z",
            "2011-03-28T10:03:09Z",
            "2011-04-29T10:02:57Z",
            "2011-05-07T10:06:55Z",
            "2012-04-07T10:07:23Z",
            "2012-05-25T10:07:54Z",
            "2013-03-25T10:09:22Z",
            "2013-03-27T10:14:18Z",
            "2013-07-07T10:15:18Z",
            "2013-07-23T10:15:17Z",
            "2014-03-12T10:10:08Z",
            "2014-03-28T10:10:16Z",
            "2014-06-08T10:12:59Z",
            "2014-08-27T10:13:23Z",
            "2014-09-04T10:10:58Z",
            "2015-08-14T10:13:01Z",
            "2015-08-22T10:13:10Z",
            "2015-09-07T10:13:12Z",
            "2015-10-25T10:13:41Z",
            "2016-05-04T10:15:42Z",
            "2016-10-03T10:13:34Z",
            "2017-02-24T10:13:12Z",
            "2017-03-28T10:12:55Z",
            "2017-05-23T10:15:49Z",
            "2017-08-11T10:15:56Z",
            "2018-03-31T10:12:46Z",
            "2018-05-10T10:13:36Z",
            "2018-05-18T10:12:18Z",
            "2018-06-03T10:12:06Z",
            "2018-06-27T10:12:47Z",
            "2018-07-21T10:12:31Z",
            "2019-04-19T10:12:45Z",
            "2019-05-13T10:04:08Z",
            "2019-05-29T10:03:32Z",
            "2019-06-22T10:13:11Z",
            "2019-08-25T10:13:30Z",
            "2019-09-18T09:59:03Z",
            "2019-10-28T10:13:43Z",
            "2020-04-21T10:12:52Z",
            "2020-05-31T09:45:50Z",
            "2020-06-24T10:13:03Z",
            "2021-03-23T10:13:08Z",
            "2021-04-16T09:23:44Z",
            "2021-06-03T09:19:40Z",
            "2021-08-22T09:12:51Z",
            "2021-08-30T10:13:32Z",
            "2021-10-17T10:13:45Z",
            "2022-04-11T10:13:08Z",
            "2022-04-19T10:13:06Z",
            "2022-05-06T08:47:24Z",
            "2022-08-25T10:13:33Z",
            "2023-03-05T10:13:32Z",
            "2023-04-22T10:13:10Z",
            "2023-04-30T10:12:48Z",
            "2023-05-08T10:12:58Z",
            "2023-05-18T08:08:31Z",
            "2023-05-24T10:12:48Z",
            "2023-06-09T10:12:43Z"
        ]
    }
}
